setup.py
lib/mrmr/__init__.py
lib/mrmr/_basemrmr.py
lib/mrmr/_discretemrmr.py
lib/mrmr/_efficientcacm.py
lib/mrmr/_fastcaim.py
lib/mrmr/_fastcaimmrmr.py
lib/mrmr/_logging.py
lib/mrmr/_mixedmodemrmr.py
lib/mrmr/_mixedmrmr.py
lib/mrmr/_phylomrmr.py
lib/mrmr/_uithread.py
lib/mrmr/_kde/__init__.py
lib/mrmr/_kde/_data.py
lib/mrmr/_kde/_diffusionkde.py
lib/mrmr/_kde/_gaussiankde.py
mrmr.egg-info/PKG-INFO
mrmr.egg-info/SOURCES.txt
mrmr.egg-info/dependency_links.txt
mrmr.egg-info/top_level.txt
scripts/mrmr