Metadata-Version: 1.1
Name: mrmr
Version: 0.9.1
Summary: minimum redundancy maximum relevance feature selection
Home-page: http://github.com/nlhepler/mrmr
Author: N Lance Hepler
Author-email: nlhepler@gmail.com
License: GNU GPL version 2
Platform: UNKNOWN
Requires: fakemp
Requires: numpy
